README.md
setup.py
z_orm_pg.egg-info/PKG-INFO
z_orm_pg.egg-info/SOURCES.txt
z_orm_pg.egg-info/dependency_links.txt
z_orm_pg.egg-info/entry_points.txt
z_orm_pg.egg-info/requires.txt
z_orm_pg.egg-info/top_level.txt
zormpg/__init__.py
zormpg/base.py
zormpg/connect.py
zormpg/dict_model.py
zormpg/models.py