Metadata-Version: 1.0
Name: z-orm-pg
Version: 0.1.0
Summary: An orm for postgresql using peewee
Home-page: http://127.0.0.1
Author: homo-zhou
Author-email: 408088242@qq.com
License: UNKNOWN
Platform: UNKNOWN
